tgtrader/__init__.py
tgtrader/common.py
tgtrader/data.py
tgtrader/strategy.py
tgtrader/strategy_config.py
tgtrader/bt/__init__.py
tgtrader/bt/algos.py
tgtrader/bt/backtest.py
tgtrader/bt/core.py
tgtrader/dao/__init__.py
tgtrader/dao/common.py
tgtrader/dao/t_api_key.py
tgtrader/dao/t_flow.py
tgtrader/dao/t_flow_node.py
tgtrader/dao/t_llm_template.py
tgtrader/dao/t_news_datasource.py
tgtrader/dao/t_rss_source.py
tgtrader/dao/t_sql_history_model.py
tgtrader/dao/t_task.py
tgtrader/dao/t_user.py
tgtrader/dao/t_user_strategy.py
tgtrader/dao/t_user_table_meta.py
tgtrader/data_provider/__init__.py
tgtrader/data_provider/data_provider_akshare.py
tgtrader/data_provider/index_data_query.py
tgtrader/data_provider/dao/__init__.py
tgtrader/data_provider/dao/akshare/__init__.py
tgtrader/data_provider/dao/akshare/common.py
tgtrader/data_provider/dao/akshare/t_etf_kdata.py
tgtrader/data_provider/dao/akshare/t_kdata.py
tgtrader/data_provider/dao/akshare/t_meta.py
tgtrader/data_provider/dao/models/__init__.py
tgtrader/data_provider/dao/models/common.py
tgtrader/data_provider/dao/models/t_etf_kdata_model.py
tgtrader/data_provider/dao/models/t_kdata_model.py
tgtrader/data_provider/dao/models/t_meta_model.py
tgtrader/data_provider/service/__init__.py
tgtrader/data_provider/service/akshare_data_service.py
tgtrader/factor/__init__.py
tgtrader/factor/factor.py
tgtrader/flow/__init__.py
tgtrader/flow/base.py
tgtrader/flow/flow.py
tgtrader/flow/nodes/__init__.py
tgtrader/flow/nodes/processor_llm.py
tgtrader/flow/nodes/processor_python.py
tgtrader/flow/nodes/processor_sql.py
tgtrader/flow/nodes/sink_db.py
tgtrader/flow/nodes/source_db.py
tgtrader/flow/nodes/source_rss.py
tgtrader/gateway/__init__.py
tgtrader/gateway/futu/__init__.py
tgtrader/gateway/futu/common.py
tgtrader/gateway/futu/defs.py
tgtrader/gateway/futu/futu_option_gateway.py
tgtrader/gateway/futu/futu_stock_gateway.py
tgtrader/gateway/futu/futu_trade_gateway.py
tgtrader/images/assets_etf2.png
tgtrader/images/assets_etf3.png
tgtrader-1.3.5.dist-info/LICENSE
tgtrader-1.3.5.dist-info/METADATA
tgtrader-1.3.5.dist-info/WHEEL
tgtrader-1.3.5.dist-info/top_level.txt
tgtrader-1.3.5.dist-info/RECORD
