Metadata-Version: 2.2
Name: tgtrader
Version: 1.3.5
Summary: TianGong Quantitative Investment Research Analysis Client
Author-email: smartian <smartian@163.com>
Maintainer-email: smartian <smartian@163.com>
License: MPL-2.0
Project-URL: Homepage, https://github.com/smartian1/tgtrader
Keywords: quantitative,trading,investment,analysis
Classifier: Programming Language :: Python :: 3
Classifier: License :: OSI Approved :: MIT License
Classifier: Operating System :: OS Independent
Requires-Python: >=3.9
License-File: LICENSE
Requires-Dist: pandas==1.5.3
Requires-Dist: numpy==1.26.4
Requires-Dist: matplotlib==3.5.3
Requires-Dist: ffn==1.1.1
Requires-Dist: loguru==0.7.3
Requires-Dist: akshare
Requires-Dist: tqdm==4.67.1
Requires-Dist: cython==3.0.11
Requires-Dist: pyprind==2.11.3
Requires-Dist: streamlit==1.41.1
Requires-Dist: peewee==3.17.8
Requires-Dist: bcrypt==4.2.1
Requires-Dist: pydantic==2.10.4
Requires-Dist: streamlit-aggrid==1.0.5
Requires-Dist: duckdb==1.1.3
Requires-Dist: arrow==1.3.0
Requires-Dist: more-itertools==10.5.0
Requires-Dist: plotly==5.24.1
Requires-Dist: nbconvert==7.16.5
Requires-Dist: streamlit-flow-component==1.5.0
Requires-Dist: streamlit-ace==0.1.1
Requires-Dist: streamlit-shadcn-ui==0.1.18
Requires-Dist: cryptography==44.0.0
Requires-Dist: feedparser==6.0.11
Requires-Dist: openai==1.60.0
Requires-Dist: apscheduler==3.11.0
Requires-Dist: futu-api
Requires-Dist: statsmodels==0.14.4
